higuchi_fractal/__init__.py
higuchi_fractal/higuchi_fractal.py
higuchi_fractal-0.1.0.dist-info/METADATA
higuchi_fractal-0.1.0.dist-info/WHEEL
higuchi_fractal-0.1.0.dist-info/top_level.txt
higuchi_fractal-0.1.0.dist-info/RECORD
